SWaN_accel/LogisticRegression_all_data_F1score_0.70.sav
SWaN_accel/StandardScalar_all_data.sav
SWaN_accel/TMP.py
SWaN_accel/__init__.py
SWaN_accel/_helper.py
SWaN_accel/_root.py
SWaN_accel/activation.py
SWaN_accel/classify.py
SWaN_accel/config.py
SWaN_accel/detect_peaks.py
SWaN_accel/energy.py
SWaN_accel/feature_set.py
SWaN_accel/feature_set_SWaN.py
SWaN_accel/orientation.py
SWaN_accel/setup.py
SWaN_accel/signal_magnitude.py
SWaN_accel/spectrum.py
SWaN_accel/stats.py
SWaN_accel/swan_first_pass.py
SWaN_accel/swan_first_pass_using_csv.py
SWaN_accel/swan_second_pass.py
SWaN_accel/swan_second_pass_using_csv.py
SWaN_accel/swan_second_pass_using_df.py
SWaN_accel/utils.py
SWaN_accel-1.18.dist-info/LICENSE
SWaN_accel-1.18.dist-info/METADATA
SWaN_accel-1.18.dist-info/WHEEL
SWaN_accel-1.18.dist-info/top_level.txt
SWaN_accel-1.18.dist-info/RECORD
