Metadata-Version: 2.1
Name: SWaN-accel
Version: 1.18
Summary: A pacakge to classify sleep-wear, wake-wear, and non-wear in accelerometer dataset.
Home-page: https://bitbucket.org/mhealthresearchgroup/packageswanfortime.git
Author: binodtc
Author-email: binod.thapachhetry@gmail.com
Classifier: Programming Language :: Python :: 3
Classifier: License :: OSI Approved :: MIT License
Classifier: Operating System :: OS Independent
Requires-Python: >=3.6
License-File: LICENSE
Requires-Dist: scikit-learn (==0.23.2)
